{
  "roles": [
    {
      "code": "WOLF",
      "name": "狼人",
      "camp": "狼人阵营",
      "description": "狼人是狼人阵营的核心角色。每晚狼人们会一起讨论并选择一名玩家进行袭击。狼人需要隐藏自己的身份，在白天的讨论中误导好人阵营。",
      "abilities": ["夜晚与其他狼人一起选择袭击目标"],
      "win_condition": "当狼人数量大于等于好人数量时，狼人阵营获胜",
      "icon": "🐺"
    },
    {
      "code": "VILLAGER",
      "name": "村民",
      "camp": "好人阵营",
      "description": "村民是好人阵营的普通角色，没有特殊技能。村民需要通过白天的讨论和投票来找出狼人，保护村庄的安全。",
      "abilities": ["白天投票处决可疑玩家"],
      "win_condition": "当所有狼人被消灭时，好人阵营获胜",
      "icon": "👨‍🌾"
    },
    {
      "code": "SEER",
      "name": "预言家",
      "camp": "好人阵营",
      "description": "预言家是好人阵营最重要的神职角色。每晚可以查验一名玩家的阵营身份（狼人或好人）。预言家需要合理利用查验信息，带领好人找出狼人。",
      "abilities": ["每晚查验一名玩家的阵营"],
      "win_condition": "当所有狼人被消灭时，好人阵营获胜",
      "icon": "🔮"
    },
    {
      "code": "WITCH",
      "name": "女巫",
      "camp": "好人阵营",
      "description": "女巫拥有两瓶药水：一瓶解药可以救活当晚被狼人袭击的玩家，一瓶毒药可以毒死任意一名玩家。每种药水只能使用一次。",
      "abilities": ["解药：救活被狼人袭击的玩家", "毒药：毒死任意一名玩家"],
      "win_condition": "当所有狼人被消灭时，好人阵营获胜",
      "icon": "🧙‍♀️"
    },
    {
      "code": "HUNTER",
      "name": "猎人",
      "camp": "好人阵营",
      "description": "猎人在被投票处决或被狼人袭击死亡时，可以选择开枪带走一名玩家。但如果是被女巫毒死，则不能开枪。",
      "abilities": ["死亡时可以开枪带走一名玩家（被毒死除外）"],
      "win_condition": "当所有狼人被消灭时，好人阵营获胜",
      "icon": "🏹"
    },
    {
      "code": "GUARD",
      "name": "守卫",
      "camp": "好人阵营",
      "description": "守卫每晚可以选择守护一名玩家（包括自己），被守护的玩家当晚不会被狼人袭击致死。守卫不能连续两晚守护同一名玩家。",
      "abilities": ["每晚守护一名玩家免受狼人袭击"],
      "win_condition": "当所有狼人被消灭时，好人阵营获胜",
      "icon": "🛡️"
    },
    {
      "code": "CUPID",
      "name": "丘比特",
      "camp": "好人阵营",
      "description": "丘比特在第一个夜晚可以选择两名玩家成为情侣。情侣之间会知道彼此的身份，如果其中一人死亡，另一人也会殉情而死。如果情侣分属不同阵营，则他们的胜利条件变为：只有情侣存活时获胜。",
      "abilities": ["第一夜选择两名玩家成为情侣"],
      "win_condition": "当所有狼人被消灭时获胜；若情侣跨阵营，则情侣存活时获胜",
      "icon": "💘"
    },
    {
      "code": "IDIOT",
      "name": "白痴",
      "camp": "好人阵营",
      "description": "白痴被投票处决时会翻牌亮出身份，然后免死一次。但翻牌后白痴将失去投票权，只能发言不能投票。白痴被狼人袭击或女巫毒死时正常死亡。",
      "abilities": ["被投票处决时免死一次，但失去投票权"],
      "win_condition": "当所有狼人被消灭时，好人阵营获胜",
      "icon": "🤪"
    },
    {
      "code": "ELDER",
      "name": "长老",
      "camp": "好人阵营",
      "description": "长老拥有两条命。第一次被狼人袭击时不会死亡，但如果被女巫毒死或被投票处决，则直接死亡。长老死亡时，如果是被好人阵营的技能或投票杀死，所有神职将失去技能。",
      "abilities": ["抵挡一次狼人袭击"],
      "win_condition": "当所有狼人被消灭时，好人阵营获胜",
      "icon": "👴"
    },
    {
      "code": "WOLF_KING",
      "name": "狼王",
      "camp": "狼人阵营",
      "description": "狼王是狼人阵营的特殊角色。狼王在被投票处决时可以选择带走一名玩家（类似猎人）。狼王被毒死时不能发动技能。",
      "abilities": ["夜晚与狼人一起袭击", "被投票处决时可带走一人"],
      "win_condition": "当狼人数量大于等于好人数量时，狼人阵营获胜",
      "icon": "👑"
    },
    {
      "code": "WHITE_WOLF",
      "name": "白狼王",
      "camp": "狼人阵营",
      "description": "白狼王是狼人阵营的特殊角色。白狼王可以在某个夜晚选择自爆，自爆时可以带走一名玩家（包括狼队友）。白狼王被预言家查验时显示为好人。",
      "abilities": ["夜晚与狼人一起袭击", "可选择自爆带走一人", "被查验显示为好人"],
      "win_condition": "当狼人数量大于等于好人数量时，狼人阵营获胜",
      "icon": "🐺‍❄️"
    },
    {
      "code": "BEAUTY",
      "name": "狼美人",
      "camp": "狼人阵营",
      "description": "狼美人是狼人阵营的特殊角色。狼美人每晚可以选择魅惑一名玩家，被魅惑的玩家如果在当晚对狼美人使用技能，则会反噬死亡。",
      "abilities": ["夜晚与狼人一起袭击", "每晚可魅惑一名玩家"],
      "win_condition": "当狼人数量大于等于好人数量时，狼人阵营获胜",
      "icon": "💋"
    }
  ]
}
